{
  "last_update": "2026-07-13T11:48:17.684360Z",
  "station_name": "כוכב השחר",
  "solarPanel": 10262,
  "temperature": {
    "current": 32.9,
    "max": 34.2,
    "max_time": "15:00",
    "min": 20.8,
    "min_time": "04:45"
  },
  "wind": {
    "speed": 8.3,
    "direction": "מזרח",
    "max": 17.3,
    "max_time": "15:30"
  },
  "rain": {
    "today": 0,
    "lastHour": 0,
    "week": 0,
    "season": 331.2,
    "daily_7d": [
      0,
      0,
      0,
      0,
      0,
      0,
      0
    ]
  }
}