{
  "last_update": "2026-05-03T20:30:33.064327Z",
  "station_name": "כוכב השחר",
  "solarPanel": 0,
  "temperature": {
    "current": 13.8,
    "max": 27.6,
    "max_time": "10:45",
    "min": 13.7,
    "min_time": "23:00"
  },
  "wind": {
    "speed": 7.2,
    "direction": "צפון",
    "max": 18.4,
    "max_time": "16:15"
  },
  "rain": {
    "today": 0,
    "lastHour": 0,
    "week": 0,
    "season": 330.6,
    "daily_7d": [
      0,
      0,
      0,
      0,
      0,
      0,
      0
    ]
  }
}