{
  "last_update": "2026-06-10T10:47:51.276898Z",
  "station_name": "כוכב השחר",
  "solarPanel": 10175,
  "temperature": {
    "current": 31.7,
    "max": 32.6,
    "max_time": "16:30",
    "min": 20.9,
    "min_time": "04:30"
  },
  "wind": {
    "speed": 3.6,
    "direction": "ד-מז",
    "max": 16.9,
    "max_time": "15:30"
  },
  "rain": {
    "today": 0,
    "lastHour": 0,
    "week": 0,
    "season": 331.2,
    "daily_7d": [
      0,
      0,
      0,
      0,
      0,
      0,
      0
    ]
  }
}