{
  "last_update": "2026-06-30T02:05:21.202158Z",
  "station_name": "כוכב השחר",
  "solarPanel": 0,
  "temperature": {
    "current": 24.0,
    "max": 33.8,
    "max_time": "15:30",
    "min": 22.0,
    "min_time": "05:45"
  },
  "wind": {
    "speed": 3.2,
    "direction": "צ-מע",
    "max": 19.8,
    "max_time": "16:15"
  },
  "rain": {
    "today": 0,
    "lastHour": 0,
    "week": 0,
    "season": 331.2,
    "daily_7d": [
      0,
      0,
      0,
      0,
      0,
      0,
      0
    ]
  }
}