{
  "last_update": "2026-04-17T12:52:40.912619Z",
  "station_name": "כוכב השחר",
  "solarPanel": 7032,
  "temperature": {
    "current": 24.4,
    "max": 33.8,
    "max_time": "16:15",
    "min": 20.7,
    "min_time": "06:30"
  },
  "wind": {
    "speed": 3.6,
    "direction": "מזרח",
    "max": 6.1,
    "max_time": "20:30"
  },
  "rain": {
    "today": 0,
    "lastHour": 0,
    "week": 0,
    "season": 330.6,
    "daily_7d": [
      0,
      0,
      0,
      0,
      0,
      0,
      0
    ]
  }
}