{
  "last_update": "2026-07-22T17:59:54.872642Z",
  "station_name": "כוכב השחר",
  "solarPanel": 315,
  "temperature": {
    "current": 28.2,
    "max": 36.9,
    "max_time": "13:45",
    "min": 23.5,
    "min_time": "06:15"
  },
  "wind": {
    "speed": 6.8,
    "direction": "צפון",
    "max": 13.3,
    "max_time": "15:00"
  },
  "rain": {
    "today": 0,
    "lastHour": 0,
    "week": 0,
    "season": 331.2,
    "daily_7d": [
      0,
      0,
      0,
      0,
      0,
      0,
      0
    ]
  }
}