{
  "last_update": "2026-05-04T15:01:24.236276Z",
  "station_name": "כוכב השחר",
  "solarPanel": 9990,
  "temperature": {
    "current": 16.8,
    "max": 19.2,
    "max_time": "13:30",
    "min": 10.8,
    "min_time": "04:45"
  },
  "wind": {
    "speed": 9.4,
    "direction": "צפון",
    "max": 16.6,
    "max_time": "20:15"
  },
  "rain": {
    "today": 0,
    "lastHour": 0,
    "week": 0,
    "season": 330.6,
    "daily_7d": [
      0,
      0,
      0,
      0,
      0,
      0,
      0
    ]
  }
}