{
  "last_update": "2026-02-23T23:32:16.158186Z",
  "station_name": "כוכב השחר",
  "solarPanel": 0,
  "temperature": {
    "current": 7.9,
    "max": 16.1,
    "max_time": "10:30",
    "min": 7.9,
    "min_time": "01:00"
  },
  "wind": {
    "speed": 6.1,
    "direction": "צפון",
    "max": 15.1,
    "max_time": "17:00"
  },
  "rain": {
    "today": 1.4,
    "lastHour": 1.4,
    "week": 1.6,
    "season": 262.8,
    "daily_7d": [
      0,
      0.2,
      0,
      0,
      0,
      0,
      1.4
    ]
  }
}