{
  "last_update": "2026-03-03T16:33:45.830099Z",
  "station_name": "כוכב השחר",
  "solarPanel": 2072,
  "temperature": {
    "current": 13.0,
    "max": 19.7,
    "max_time": "14:45",
    "min": 7.9,
    "min_time": "06:15"
  },
  "wind": {
    "speed": 4.0,
    "direction": "צפון",
    "max": 15.1,
    "max_time": "21:30"
  },
  "rain": {
    "today": 0,
    "lastHour": 0,
    "week": 3.4,
    "season": 267.0,
    "daily_7d": [
      0,
      1.4,
      2.0,
      0,
      0,
      0,
      0
    ]
  }
}