{
  "last_update": "2026-07-20T08:34:44.419120Z",
  "station_name": "כוכב השחר",
  "solarPanel": 10297,
  "temperature": {
    "current": 32.2,
    "max": 37.5,
    "max_time": "14:15",
    "min": 24.3,
    "min_time": "03:45"
  },
  "wind": {
    "speed": 5.8,
    "direction": "ד-מז",
    "max": 14.4,
    "max_time": "17:30"
  },
  "rain": {
    "today": 0,
    "lastHour": 0,
    "week": 0,
    "season": 331.2,
    "daily_7d": [
      0,
      0,
      0,
      0,
      0,
      0,
      0
    ]
  }
}